napari_umap/__init__.py
napari_umap/_widget.py
napari_umap/napari.yaml
napari_umap/_tests/__init__.py
napari_umap/_tests/test_widget.py
napari_umap-0.0.1.dist-info/LICENSE
napari_umap-0.0.1.dist-info/METADATA
napari_umap-0.0.1.dist-info/WHEEL
napari_umap-0.0.1.dist-info/entry_points.txt
napari_umap-0.0.1.dist-info/top_level.txt
napari_umap-0.0.1.dist-info/RECORD
