Metadata-Version: 2.1
Name: napari-umap
Version: 0.0.1
Summary: A simple plugin to use with napari
Home-page: https://github.com/royerlab/napari-umap
Author: Jordao Bragantini
Author-email: jordao.bragantini@czbiohub.org
License: BSD-3-Clause
Project-URL: Bug Tracker, https://github.com/royerlab/napari-umap/issues
Project-URL: Documentation, https://github.com/royerlab/napari-umap#README.md
Project-URL: Source Code, https://github.com/royerlab/napari-umap
Project-URL: User Support, https://github.com/royerlab/napari-umap/issues
Classifier: Development Status :: 2 - Pre-Alpha
Classifier: Framework :: napari
Classifier: Intended Audience :: Developers
Classifier: License :: OSI Approved :: BSD License
Classifier: Operating System :: OS Independent
Classifier: Programming Language :: Python
Classifier: Programming Language :: Python :: 3
Classifier: Programming Language :: Python :: 3 :: Only
Classifier: Programming Language :: Python :: 3.8
Classifier: Programming Language :: Python :: 3.9
Classifier: Programming Language :: Python :: 3.10
Classifier: Topic :: Scientific/Engineering :: Image Processing
Requires-Python: >=3.8
License-File: LICENSE
Requires-Dist: numpy
Requires-Dist: magicgui
Requires-Dist: qtpy
Provides-Extra: testing
Requires-Dist: tox ; extra == 'testing'
Requires-Dist: pytest ; extra == 'testing'
Requires-Dist: pytest-cov ; extra == 'testing'
Requires-Dist: pytest-qt ; extra == 'testing'
Requires-Dist: napari ; extra == 'testing'
Requires-Dist: pyqt5 ; extra == 'testing'
